MANIFEST.in
README.md
setup.cfg
setup.py
GNetTrainer/Training.py
GNetTrainer/__init__.py
GNetTrainer/main.py
GNetTrainer/predict.py
GNetTrainer.egg-info/PKG-INFO
GNetTrainer.egg-info/SOURCES.txt
GNetTrainer.egg-info/dependency_links.txt
GNetTrainer.egg-info/entry_points.txt
GNetTrainer.egg-info/requires.txt
GNetTrainer.egg-info/top_level.txt
GNetTrainer/com_in_ineuron_ai_utils/__init__.py
GNetTrainer/com_in_ineuron_ai_utils/utils.py
GNetTrainer/static/css/style.css
GNetTrainer/static/css/assets/img/GNet.png
GNetTrainer/static/css/assets/img/home.JPG
GNetTrainer/static/css/assets/img/img.jpeg
GNetTrainer/static/css/assets/img/predict.JPG
GNetTrainer/static/css/assets/img/train1.JPG
GNetTrainer/static/css/assets/img/train2.JPG
GNetTrainer/templates/index.html
GNetTrainer/templates/predict.html
GNetTrainer/templates/train.html
GNetTrainer/utils/__init__.py
GNetTrainer/utils/close_match.py
GNetTrainer/utils/config.py
GNetTrainer/utils/data_management.py
GNetTrainer/utils/input.py
GNetTrainer/utils/model.py
GNetTrainer/utils/model_config.py