Metadata-Version: 1.1
Name: GNetTrainer
Version: 2.0
Summary: Image classification trainer
Home-page: https://github.com/Rishav-hub/GNetTrainer-package.git
Author: Rishav-hub
Author-email: 9930046@gmail.com
License: MIT
Keywords: gnetrainer
Platform: UNKNOWN
Classifier: Development Status :: 3 - Alpha
Classifier: Intended Audience :: Developers
Classifier: Topic :: Software Development :: Build Tools
Classifier: License :: OSI Approved :: MIT License
Classifier: Programming Language :: Python :: 3
Classifier: Programming Language :: Python :: 3.4
Classifier: Programming Language :: Python :: 3.5
Classifier: Programming Language :: Python :: 3.6
